README.md
setup.cfg
setup.py
umaat/__init__.py
umaat.egg-info/PKG-INFO
umaat.egg-info/SOURCES.txt
umaat.egg-info/dependency_links.txt
umaat.egg-info/requires.txt
umaat.egg-info/top_level.txt